Metadata-Version: 2.4
Name: llama-index-vector-stores-oceanbase
Version: 0.4.0
Summary: llama-index vector-stores oceanbase integration
Author-email: GITHUBear <shanhaikang.shk@oceanbase.com>
License-Expression: MIT
License-File: LICENSE
Requires-Python: <4.0,>=3.10
Requires-Dist: llama-index-core<0.15,>=0.13.0
Requires-Dist: pyobvector<0.3,>=0.2.0
